pycounts_zanan_524/__init__.py
pycounts_zanan_524/plotting.py
pycounts_zanan_524/pycounts.py
pycounts_zanan_524-0.1.0.dist-info/LICENSE
pycounts_zanan_524-0.1.0.dist-info/METADATA
pycounts_zanan_524-0.1.0.dist-info/WHEEL
pycounts_zanan_524-0.1.0.dist-info/RECORD
