Metadata-Version: 2.3
Name: pycounts_zanan_524
Version: 0.1.0
Summary: Count words from a text file!
License: MIT
Author: Zanan Pech
Requires-Python: >=3.11
Classifier: License :: OSI Approved :: MIT License
Classifier: Programming Language :: Python :: 3
Classifier: Programming Language :: Python :: 3.11
Classifier: Programming Language :: Python :: 3.12
Classifier: Programming Language :: Python :: 3.13
Requires-Dist: matplotlib (>=3.10.0)
